[{"id":"710cdf000","mode":"killer","givens":[0,0,0,0,0,0,0,0,0,0,0,0,0,0,0,0,0,0,0,0,0,0,0,0,0,0,0,0,0,0,0,0,0,0,0,0,0,0,0,0,0,0,0,0,0,0,0,0,0,0,0,0,0,0,0,0,0,0,0,0,0,0,0,0,0,0,0,0,0,0,0,0,0,0,0,0,0,0,0,0,0],"solution":[9,2,6,3,8,7,1,4,5,1,5,3,6,2,4,7,9,8,8,4,7,1,5,9,3,6,2,2,6,8,7,1,3,9,5,4,4,1,9,2,6,5,8,7,3,7,3,5,4,9,8,6,2,1,5,9,4,8,3,6,2,1,7,3,7,2,9,4,1,5,8,6,6,8,1,5,7,2,4,3,9],"cages":[{"cells":[0,9,1,18,10],"sum":25},{"cells":[2,11,3,20],"sum":19},{"cells":[4,13,5],"sum":17},{"cells":[6,15,7],"sum":12},{"cells":[8,17,26,16],"sum":24},{"cells":[12,21,30],"sum":14},{"cells":[14,23,32,22],"sum":21},{"cells":[19,28],"sum":10},{"cells":[24,33,25,34],"sum":23},{"cells":[27,36],"sum":6},{"cells":[29,38,47,37],"sum":23},{"cells":[31,40],"sum":7},{"cells":[35,44,53],"sum":8},{"cells":[39,48],"sum":6},{"cells":[41,50,42,51],"sum":27},{"cells":[43,52,61],"sum":10},{"cells":[45,54,46,63],"sum":18},{"cells":[49,58],"sum":12},{"cells":[55,64,56,73],"sum":28},{"cells":[57,66,75,65],"sum":24},{"cells":[59,68,60,69,78],"sum":18},{"cells":[62,71,80,70,79],"sum":33},{"cells":[67,76,77],"sum":13},{"cells":[72],"sum":6},{"cells":[74],"sum":1}]},{"id":"71hqm2001","mode":"killer","givens":[0,0,0,0,0,0,0,0,0,0,0,0,0,0,0,0,0,0,0,0,0,0,0,0,0,0,0,0,0,0,0,0,0,0,0,0,0,0,0,0,0,0,0,0,0,0,0,0,0,0,0,0,0,0,0,0,0,0,0,0,0,0,0,0,0,0,0,0,0,0,0,0,0,0,0,0,0,0,0,0,0],"solution":[5,4,1,8,7,2,6,9,3,7,3,9,4,5,6,2,1,8,2,8,6,9,1,3,5,7,4,4,1,2,3,9,5,7,8,6,9,7,3,6,2,8,4,5,1,8,6,5,1,4,7,3,2,9,1,2,8,7,3,4,9,6,5,3,9,7,5,6,1,8,4,2,6,5,4,2,8,9,1,3,7],"cages":[{"cells":[0,9,1,18,10],"sum":21},{"cells":[2,11],"sum":10},{"cells":[3,12],"sum":12},{"cells":[4,13,5,14,6],"sum":26},{"cells":[7,16,8],"sum":13},{"cells":[15,24,33],"sum":14},{"cells":[17,26,35],"sum":18},{"cells":[19,28,20,29,21],"sum":26},{"cells":[22,31,23,32],"sum":18},{"cells":[25,34],"sum":15},{"cells":[27,36,45,37],"sum":28},{"cells":[30,39],"sum":9},{"cells":[38,47,56,46],"sum":22},{"cells":[40,49,41,50,42],"sum":25},{"cells":[43,52],"sum":7},{"cells":[44,53],"sum":10},{"cells":[48,57,66],"sum":13},{"cells":[51,60],"sum":12},{"cells":[54,63,55,64],"sum":15},{"cells":[58,67,59,76],"sum":21},{"cells":[61,70,62],"sum":15},{"cells":[65,74,73,75,72],"sum":24},{"cells":[68,77,69],"sum":18},{"cells":[71,80,79,78],"sum":13}]},{"id":"71j7fo002","mode":"killer","givens":[0,0,0,0,0,0,0,0,0,0,0,0,0,0,0,0,0,0,0,0,0,0,0,0,0,0,0,0,0,0,0,0,0,0,0,0,0,0,0,0,0,0,0,0,0,0,0,0,0,0,0,0,0,0,0,0,0,0,0,0,0,0,0,0,0,0,0,0,0,0,0,0,0,0,0,0,0,0,0,0,0],"solution":[2,6,8,4,7,5,9,3,1,4,1,3,6,9,2,8,7,5,9,5,7,8,1,3,2,6,4,3,2,6,7,4,8,1,5,9,5,7,9,2,6,1,3,4,8,1,8,4,3,5,9,6,2,7,6,9,2,5,8,4,7,1,3,8,3,5,1,2,7,4,9,6,7,4,1,9,3,6,5,8,2],"cages":[{"cells":[0,9,1,18],"sum":21},{"cells":[2,11,3,12],"sum":21},{"cells":[4,13,5],"sum":21},{"cells":[6,15,7,24,14],"sum":24},{"cells":[8,17,26,16],"sum":17},{"cells":[10,19,28,20,29],"sum":21},{"cells":[21,30,22,39],"sum":18},{"cells":[23,32,41,31,33],"sum":17},{"cells":[25,34,43],"sum":15},{"cells":[27,36,45,37,46],"sum":24},{"cells":[35,44,53,62,52],"sum":29},{"cells":[38,47,56],"sum":15},{"cells":[40,49,58],"sum":19},{"cells":[42,51,60],"sum":16},{"cells":[48,57,66],"sum":9},{"cells":[50,59,68],"sum":20},{"cells":[54,63,55,64],"sum":26},{"cells":[61,70,79,69,71],"sum":28},{"cells":[65,74],"sum":6},{"cells":[67,76,75,77,78],"sum":25},{"cells":[72,73],"sum":11},{"cells":[80],"sum":2}]},{"id":"72c7wz003","mode":"killer","givens":[0,0,0,0,0,0,0,0,0,0,0,0,0,0,0,0,0,0,0,0,0,0,0,0,0,0,0,0,0,0,0,0,0,0,0,0,0,0,0,0,0,0,0,0,0,0,0,0,0,0,0,0,0,0,0,0,0,0,0,0,0,0,0,0,0,0,0,0,0,0,0,0,0,0,0,0,0,0,0,0,0],"solution":[5,2,1,6,4,9,8,3,7,7,8,3,1,2,5,9,4,6,9,6,4,8,3,7,5,1,2,2,1,9,4,8,6,7,5,3,3,4,6,5,7,1,2,8,9,8,7,5,2,9,3,1,6,4,1,5,7,3,6,2,4,9,8,4,3,2,9,1,8,6,7,5,6,9,8,7,5,4,3,2,1],"cages":[{"cells":[0,9,1,18],"sum":23},{"cells":[2,11],"sum":4},{"cells":[3,12,4],"sum":11},{"cells":[5,14,6],"sum":22},{"cells":[7,16,8],"sum":14},{"cells":[10,19,28,20,29],"sum":28},{"cells":[13,22,31],"sum":13},{"cells":[15,24],"sum":14},{"cells":[17,26,35,25],"sum":12},{"cells":[21,30],"sum":12},{"cells":[23,32,41],"sum":14},{"cells":[27,36,45,37],"sum":17},{"cells":[33,42,34],"sum":14},{"cells":[38,47,39,56],"sum":23},{"cells":[40,49,58,48],"sum":24},{"cells":[43,52],"sum":14},{"cells":[44,53,62],"sum":21},{"cells":[46,55,64,54],"sum":16},{"cells":[50,59],"sum":5},{"cells":[51,60],"sum":5},{"cells":[57,66,75],"sum":19},{"cells":[61,70,79,69,71],"sum":29},{"cells":[63,72,73,74],"sum":27},{"cells":[65],"sum":2},{"cells":[67,76,68,77,78],"sum":21},{"cells":[80],"sum":1}]},{"id":"76o5ts004","mode":"killer","givens":[0,0,0,0,0,0,0,0,0,0,0,0,0,0,0,0,0,0,0,0,0,0,0,0,0,0,0,0,0,0,0,0,0,0,0,0,0,0,0,0,0,0,0,0,0,0,0,0,0,0,0,0,0,0,0,0,0,0,0,0,0,0,0,0,0,0,0,0,0,0,0,0,0,0,0,0,0,0,0,0,0],"solution":[7,8,6,1,3,4,5,2,9,4,9,5,8,7,2,6,1,3,1,2,3,5,9,6,7,8,4,2,7,4,6,1,8,3,9,5,9,5,8,3,4,7,1,6,2,3,6,1,9,2,5,8,4,7,5,1,2,4,6,3,9,7,8,6,3,7,2,8,9,4,5,1,8,4,9,7,5,1,2,3,6],"cages":[{"cells":[0,9,1,10,2],"sum":34},{"cells":[3,12,4],"sum":12},{"cells":[5,14],"sum":6},{"cells":[6,15,7,24],"sum":20},{"cells":[8,17,26],"sum":16},{"cells":[11,20],"sum":8},{"cells":[13,22],"sum":16},{"cells":[16,25,34,43],"sum":24},{"cells":[18,27,19,28],"sum":12},{"cells":[21,30],"sum":11},{"cells":[23,32],"sum":14},{"cells":[29,38,47],"sum":13},{"cells":[31,40],"sum":5},{"cells":[33,42,51,41],"sum":19},{"cells":[35,44,53,62,52],"sum":26},{"cells":[36,45,37],"sum":17},{"cells":[39,48,57,49],"sum":18},{"cells":[46,55,64],"sum":10},{"cells":[50,59,68,58],"sum":23},{"cells":[54,63],"sum":11},{"cells":[56,65,74],"sum":18},{"cells":[60,69,61],"sum":20},{"cells":[66,75,67,76,77],"sum":23},{"cells":[70,79],"sum":8},{"cells":[71,80],"sum":7},{"cells":[72,73],"sum":12},{"cells":[78],"sum":2}]},{"id":"77iq69005","mode":"killer","givens":[0,0,0,0,0,0,0,0,0,0,0,0,0,0,0,0,0,0,0,0,0,0,0,0,0,0,0,0,0,0,0,0,0,0,0,0,0,0,0,0,0,0,0,0,0,0,0,0,0,0,0,0,0,0,0,0,0,0,0,0,0,0,0,0,0,0,0,0,0,0,0,0,0,0,0,0,0,0,0,0,0],"solution":[5,7,3,8,2,4,1,6,9,2,8,4,1,9,6,7,3,5,9,1,6,3,5,7,2,4,8,3,9,5,4,7,2,8,1,6,1,6,7,5,3,8,9,2,4,8,4,2,9,6,1,3,5,7,4,2,8,7,1,5,6,9,3,6,5,9,2,8,3,4,7,1,7,3,1,6,4,9,5,8,2],"cages":[{"cells":[0,9,1,10],"sum":22},{"cells":[2,11,3],"sum":15},{"cells":[4,13,5,14],"sum":21},{"cells":[6,15,7],"sum":14},{"cells":[8,17,26,16],"sum":25},{"cells":[12,21,30,20,22],"sum":19},{"cells":[18,27],"sum":12},{"cells":[19,28,37],"sum":16},{"cells":[23,32],"sum":9},{"cells":[24,33,25,34],"sum":15},{"cells":[29,38],"sum":12},{"cells":[31,40,49,39,41],"sum":29},{"cells":[35,44,53,43],"sum":19},{"cells":[36,45],"sum":9},{"cells":[42,51,60],"sum":18},{"cells":[46,55,47],"sum":8},{"cells":[48,57,66,56,58],"sum":27},{"cells":[50,59,68,77],"sum":18},{"cells":[52,61,70,62],"sum":24},{"cells":[54,63,72,64],"sum":22},{"cells":[65,74,73,75,76],"sum":23},{"cells":[67],"sum":8},{"cells":[69,78,79],"sum":17},{"cells":[71,80],"sum":3}]},{"id":"7kwroh006","mode":"killer","givens":[0,0,0,0,0,0,0,0,0,0,0,0,0,0,0,0,0,0,0,0,0,0,0,0,0,0,0,0,0,0,0,0,0,0,0,0,0,0,0,0,0,0,0,0,0,0,0,0,0,0,0,0,0,0,0,0,0,0,0,0,0,0,0,0,0,0,0,0,0,0,0,0,0,0,0,0,0,0,0,0,0],"solution":[9,4,5,3,7,6,2,1,8,7,1,2,5,9,8,3,6,4,6,8,3,2,1,4,9,5,7,8,6,1,7,3,9,4,2,5,4,2,9,1,6,5,8,7,3,3,5,7,8,4,2,6,9,1,5,3,8,6,2,7,1,4,9,1,9,6,4,5,3,7,8,2,2,7,4,9,8,1,5,3,6],"cages":[{"cells":[0,9,1,18],"sum":26},{"cells":[2,11,3,12],"sum":15},{"cells":[4,13],"sum":16},{"cells":[5,14,6,23],"sum":20},{"cells":[7,16,8,25,15],"sum":23},{"cells":[10,19,28,20,37],"sum":20},{"cells":[17,26,35],"sum":16},{"cells":[21,30,22,39,29],"sum":12},{"cells":[24,33,42,32],"sum":30},{"cells":[27,36,45,54,46],"sum":25},{"cells":[31,40,49,41,50],"sum":20},{"cells":[34,43,52,44],"sum":21},{"cells":[38,47,56],"sum":24},{"cells":[48,57,66,58,67],"sum":25},{"cells":[51,60],"sum":7},{"cells":[53,62,71,61],"sum":16},{"cells":[55,64,73],"sum":19},{"cells":[59,68,77],"sum":11},{"cells":[63,72],"sum":3},{"cells":[65,74,75],"sum":19},{"cells":[69,78,70,79],"sum":23},{"cells":[76],"sum":8},{"cells":[80],"sum":6}]},{"id":"7l5wel007","mode":"killer","givens":[0,0,0,0,0,0,0,0,0,0,0,0,0,0,0,0,0,0,0,0,0,0,0,0,0,0,0,0,0,0,0,0,0,0,0,0,0,0,0,0,0,0,0,0,0,0,0,0,0,0,0,0,0,0,0,0,0,0,0,0,0,0,0,0,0,0,0,0,0,0,0,0,0,0,0,0,0,0,0,0,0],"solution":[4,9,3,5,1,6,7,2,8,1,7,8,2,3,9,5,6,4,6,2,5,8,4,7,1,3,9,3,8,2,4,5,1,9,7,6,7,4,9,6,2,8,3,5,1,5,6,1,9,7,3,8,4,2,9,5,6,3,8,4,2,1,7,8,3,7,1,6,2,4,9,5,2,1,4,7,9,5,6,8,3],"cages":[{"cells":[0,9],"sum":5},{"cells":[1,10,2],"sum":19},{"cells":[3,12,4,13,5],"sum":17},{"cells":[6,15,7,16,8],"sum":28},{"cells":[11,20],"sum":13},{"cells":[14,23],"sum":16},{"cells":[17,26,35,25],"sum":22},{"cells":[18,27,19,28,37],"sum":23},{"cells":[21,30],"sum":12},{"cells":[22,31],"sum":9},{"cells":[24,33,42,32],"sum":14},{"cells":[29,38,47,39,48],"sum":27},{"cells":[34,43,52,44,61],"sum":18},{"cells":[36,45],"sum":12},{"cells":[40,49],"sum":9},{"cells":[41,50,59],"sum":15},{"cells":[46,55,64],"sum":14},{"cells":[51,60,69,78,68],"sum":22},{"cells":[53,62,71,80,70],"sum":26},{"cells":[54,63,72,73],"sum":20},{"cells":[56,65,57,66,58],"sum":25},{"cells":[67,76,75,77],"sum":27},{"cells":[74],"sum":4},{"cells":[79],"sum":8}]},{"id":"7lb5oo008","mode":"killer","givens":[0,0,0,0,0,0,0,0,0,0,0,0,0,0,0,0,0,0,0,0,0,0,0,0,0,0,0,0,0,0,0,0,0,0,0,0,0,0,0,0,0,0,0,0,0,0,0,0,0,0,0,0,0,0,0,0,0,0,0,0,0,0,0,0,0,0,0,0,0,0,0,0,0,0,0,0,0,0,0,0,0],"solution":[5,2,9,4,1,3,6,7,8,6,8,3,7,5,9,1,4,2,4,7,1,8,2,6,9,5,3,2,1,7,6,8,5,3,9,4,8,9,5,1,3,4,7,2,6,3,6,4,9,7,2,5,8,1,7,3,2,5,6,8,4,1,9,9,5,8,3,4,1,2,6,7,1,4,6,2,9,7,8,3,5],"cages":[{"cells":[0,9,1,18],"sum":17},{"cells":[2,11,3,20,10],"sum":25},{"cells":[4,13,5,14,6],"sum":24},{"cells":[7,16,8,25],"sum":24},{"cells":[12,21,30,22,31],"sum":31},{"cells":[15,24,33,23],"sum":19},{"cells":[17,26,35,44],"sum":15},{"cells":[19,28,37,27,29],"sum":26},{"cells":[32,41,50,40,42],"sum":21},{"cells":[34,43,52,61],"sum":20},{"cells":[36,45],"sum":11},{"cells":[38,47],"sum":9},{"cells":[39,48,57,49,66],"sum":25},{"cells":[46,55,64],"sum":14},{"cells":[51,60,69,59,78],"sum":27},{"cells":[53,62,71,80,70],"sum":28},{"cells":[54,63],"sum":16},{"cells":[56,65,74,73],"sum":20},{"cells":[58,67,76,68],"sum":20},{"cells":[72],"sum":1},{"cells":[75],"sum":2},{"cells":[77],"sum":7},{"cells":[79],"sum":3}]},{"id":"7q2oqn009","mode":"killer","givens":[0,0,0,0,0,0,0,0,0,0,0,0,0,0,0,0,0,0,0,0,0,0,0,0,0,0,0,0,0,0,0,0,0,0,0,0,0,0,0,0,0,0,0,0,0,0,0,0,0,0,0,0,0,0,0,0,0,0,0,0,0,0,0,0,0,0,0,0,0,0,0,0,0,0,0,0,0,0,0,0,0],"solution":[4,9,2,5,6,8,1,7,3,5,3,6,1,4,7,2,9,8,1,8,7,9,2,3,5,4,6,3,5,9,6,1,2,7,8,4,8,2,1,3,7,4,9,6,5,6,7,4,8,9,5,3,2,1,2,6,8,7,3,1,4,5,9,9,4,3,2,5,6,8,1,7,7,1,5,4,8,9,6,3,2],"cages":[{"cells":[0,9,1,10],"sum":21},{"cells":[2,11],"sum":8},{"cells":[3,12,4],"sum":12},{"cells":[5,14,6,15],"sum":18},{"cells":[7,16,8,25,17],"sum":31},{"cells":[13,22],"sum":6},{"cells":[18,27,19],"sum":12},{"cells":[20,29,21,38],"sum":26},{"cells":[23,32,24,33],"sum":17},{"cells":[26,35],"sum":10},{"cells":[28,37,46,36],"sum":22},{"cells":[30,39,31,40,48],"sum":25},{"cells":[34,43,52,42,44],"sum":30},{"cells":[41,50],"sum":9},{"cells":[45,54,63,55,72],"sum":30},{"cells":[47,56,65,57],"sum":22},{"cells":[49,58,67,59],"sum":18},{"cells":[51,60,69],"sum":15},{"cells":[53,62,71],"sum":17},{"cells":[61,70,79,78,80],"sum":17},{"cells":[64,73,74,75],"sum":14},{"cells":[66],"sum":2},{"cells":[68,77,76],"sum":23}]}]